pybricks_ext/__init__.py
pybricks_ext/ev3brick.py
pybricks_ext/ev3devices.py
pybricks_ext/parameters.py
pybricks_ext/speed_util.py
pybricks_ext/tools.py
lego_mp_extension-0.1.9.dist-info/LICENSE
lego_mp_extension-0.1.9.dist-info/METADATA
lego_mp_extension-0.1.9.dist-info/WHEEL
lego_mp_extension-0.1.9.dist-info/top_level.txt
lego_mp_extension-0.1.9.dist-info/RECORD
