Metadata-Version: 2.1
Name: lego-mp-extension
Version: 0.1.9
Summary: Extension for the Lego EV3 MicroPython Port
Home-page: https://github.com/klutzybubbles/lego-micropython-extension
Author: Lee Tzilantonis
Author-email: LTzilantonis@gmail.com
License: UNKNOWN
Platform: UNKNOWN
Classifier: Programming Language :: Python :: 3
Classifier: License :: OSI Approved :: MIT License
Classifier: Operating System :: OS Independent
